cliffold/__init__.py
cliffold/py.typed
cliffold-0.0.0.dist-info/LICENSE
cliffold-0.0.0.dist-info/METADATA
cliffold-0.0.0.dist-info/WHEEL
cliffold-0.0.0.dist-info/RECORD
